{
	"command.wrapWithAbbreviation": "Wrap with Abbreviation",
	"command.wrapIndividualLinesWithAbbreviation": "Wrap Individual Lines with Abbreviation",
	"command.removeTag": "Elem eltávolítása",
	"command.updateTag": "Elem módosítása",
	"command.matchTag": "Ugrás az illeszkedő párra",
	"command.balanceIn": "Egyensúlyozás (belefé)",
	"command.balanceOut": "Egyensúlyozás (kifelé)",
	"command.prevEditPoint": "Ugrás az előző szerkesztési pontra",
	"command.nextEditPoint": "Ugrás a következő szerkesztési pontra",
	"command.mergeLines": "Sorok összeolvasztása",
	"command.selectPrevItem": "Előző elem kiválasztása",
	"command.selectNextItem": "Következő elem kiválasztása",
	"command.splitJoinTag": "Elem szétbontása/összeolvasztása",
	"command.toggleComment": "Megjegyzés ki-/bekapcsolása",
	"command.evaluateMathExpression": "Matematikai kifejezés kiértékelése",
	"command.updateImageSize": "Képméret módosítása",
	"command.reflectCSSValue": "CSS-érték tükrözése",
	"command.incrementNumberByOne": "Növelés 1-gyel",
	"command.decrementNumberByOne": "Csökkentés 1-gyel",
	"command.incrementNumberByOneTenth": "Növelés 0,1-gyel",
	"command.decrementNumberByOneTenth": "Csökkentés 0,1-gyel",
	"command.incrementNumberByTen": "Növelés 10-zel",
	"command.decrementNumberByTen": "Csökkentés 10-zel",
	"emmetSyntaxProfiles": "Define profile for specified syntax or use your own profile with specific rules.",
	"emmetExclude": "An array of languages where emmet abbreviations should not be expanded.",
	"emmetExtensionsPath": "Path to a folder containing emmet profiles and snippets.'",
	"emmetShowExpandedAbbreviation": "Shows expanded emmet abbreviations as suggestions.\nThe option \"inMarkupAndStylesheetFilesOnly\" applies to html, haml, jade, slim, xml, xsl, css, scss, sass, less and stylus.\nThe option \"always\" applies to all parts of the file regardless of markup/css.",
	"emmetShowAbbreviationSuggestions": "Shows possible emmet abbreviations as suggestions. Not applicable in stylesheets or when emmet.showExpandedAbbreviation is set to \"never\".",
	"emmetIncludeLanguages": "Enable emmet abbreviations in languages that are not supported by default. Add a mapping here between the language and emmet supported language.\n Eg: {\"vue-html\": \"html\", \"javascript\": \"javascriptreact\"}",
	"emmetVariables": "Variables to be used in emmet snippets"
}